setup.cfg
setup.py
outlier_kamakshi/__init__.py
outlier_kamakshi/basic.py
outlier_kamakshi/outlier_remover.py
outlier_kamakshi.egg-info/PKG-INFO
outlier_kamakshi.egg-info/SOURCES.txt
outlier_kamakshi.egg-info/dependency_links.txt
outlier_kamakshi.egg-info/top_level.txt