Metadata-Version: 1.2
Name: outlier-kamakshi
Version: 0.0.1
Summary: This is a package for outlier remover using row remover method.
Home-page: https://github.com/kamakshibehl/outlier_kamakshi.git
Author: kamakshi/kamakshi_behl
Author-email: kamakshi.behl22@gmail.com
License: UNKNOWN
Download-URL: https://github.com/kamakshibehl/outlier_kamakshi/archive/0.0.1.tar.gz
Platform: UNKNOWN
Classifier: Programming Language :: Python :: 3
Classifier: License :: OSI Approved :: MIT License
Classifier: Operating System :: OS Independent
Requires-Python: >=3.6
